configuration/__init__.py
configuration/injectors.py
configuration/utils.py
tests/__init__.py
tests/unit/__init__.py
tests/unit/tests_injectors_json.py
tests/unit/tests_injectors_yaml.py
tests/unit/tests_utils.py
application_config-0.0.1.dist-info/LICENSE
application_config-0.0.1.dist-info/METADATA
application_config-0.0.1.dist-info/WHEEL
application_config-0.0.1.dist-info/top_level.txt
application_config-0.0.1.dist-info/RECORD
