Metadata-Version: 2.1
Name: application-config
Version: 0.0.1
Summary: Simple decorator for injecting a configuration into classes
Home-page: https://github.com/bholten/py-application-config
Author: Brennan Holten
Author-email: brennan.holten@objectpartners.com
License: MIT
Platform: UNKNOWN
Requires-Python: >=3.6
Requires-Dist: PyYAML
